tectonic_utils/__init__.py
tectonic_utils/cover_picture.png
tectonic_utils/geodesy/__init__.py
tectonic_utils/geodesy/datums.py
tectonic_utils/geodesy/euler_pole.py
tectonic_utils/geodesy/fault_vector_functions.py
tectonic_utils/geodesy/haversine.py
tectonic_utils/geodesy/insar_vector_functions.py
tectonic_utils/geodesy/linear_elastic.py
tectonic_utils/geodesy/test/__init__.py
tectonic_utils/geodesy/test/test_conversion_functions.py
tectonic_utils/geodesy/test/test_euler_poles.py
tectonic_utils/geodesy/test/test_insar_vector_functions.py
tectonic_utils/geodesy/utilities.py
tectonic_utils/geodesy/xyz2llh.py
tectonic_utils/read_write/__init__.py
tectonic_utils/read_write/general_io.py
tectonic_utils/read_write/netcdf_read_write.py
tectonic_utils/read_write/read_kml.py
tectonic_utils/read_write/test/__init__.py
tectonic_utils/read_write/test/example_grd.grd
tectonic_utils/read_write/test/test_conversion_functions.py
tectonic_utils/seismo/MT_calculations.py
tectonic_utils/seismo/__init__.py
tectonic_utils/seismo/moment_calculations.py
tectonic_utils/seismo/second_focal_plane.py
tectonic_utils/seismo/test/__init__.py
tectonic_utils/seismo/test/test_WC.py
tectonic_utils/seismo/test/test_second_focal_plane.py
tectonic_utils/seismo/wells_and_coppersmith.py
tectonic_utils-0.2.1.dist-info/LICENSE.md
tectonic_utils-0.2.1.dist-info/METADATA
tectonic_utils-0.2.1.dist-info/WHEEL
tectonic_utils-0.2.1.dist-info/RECORD
