Metadata-Version: 2.1
Name: tectonic-utils
Version: 0.2.1
Summary: A small package of useful geophysics utilities
Home-page: https://github.com/kmaterna/Tectonic_Utils
License: MIT
Author: Kathryn Materna
Author-email: kmaterna@berkeley.edu
Requires-Python: >=3.7
Classifier: License :: OSI Approved :: MIT License
Classifier: Operating System :: OS Independent
Classifier: Programming Language :: Python :: 3
Classifier: Programming Language :: Python :: 3.7
Classifier: Programming Language :: Python :: 3.8
Classifier: Programming Language :: Python :: 3.9
Classifier: Programming Language :: Python :: 3.10
Classifier: Programming Language :: Python :: 3.11
Classifier: Programming Language :: Python :: 3.12
Requires-Dist: netCDF4
Requires-Dist: numpy (>=1.20,<2.0)
Requires-Dist: scipy
Project-URL: Repository, https://github.com/kmaterna/Tectonic_Utils
